{
  "formatVersion": 1,
  "database": {
    "version": 1,
    "identityHash": "3ef7bee3b1c15ce0649ace631416108c",
    "entities": [
      {
        "tableName": "playlists",
        "createSql": "CREATE TABLE IF NOT EXISTS `${TABLE_NAME}` (`id` INTEGER PRIMARY KEY AUTOINCREMENT NOT NULL, `name` TEXT NOT NULL, `createdAt` INTEGER NOT NULL, `updatedAt` INTEGER NOT NULL)",
        "fields": [
          {
            "fieldPath": "id",
            "columnName": "id",
            "affinity": "INTEGER",
            "notNull": true
          },
          {
            "fieldPath": "name",
            "columnName": "name",
            "affinity": "TEXT",
            "notNull": true
          },
          {
            "fieldPath": "createdAt",
            "columnName": "createdAt",
            "affinity": "INTEGER",
            "notNull": true
          },
          {
            "fieldPath": "updatedAt",
            "columnName": "updatedAt",
            "affinity": "INTEGER",
            "notNull": true
          }
        ],
        "primaryKey": {
          "autoGenerate": true,
          "columnNames": [
            "id"
          ]
        }
      },
      {
        "tableName": "playlist_songs",
        "createSql": "CREATE TABLE IF NOT EXISTS `${TABLE_NAME}` (`playlistId` INTEGER NOT NULL, `songId` INTEGER NOT NULL, `sortOrder` INTEGER NOT NULL, `addedAt` INTEGER NOT NULL, PRIMARY KEY(`playlistId`, `songId`), FOREIGN KEY(`playlistId`) REFERENCES `playlists`(`id`) ON UPDATE NO ACTION ON DELETE CASCADE )",
        "fields": [
          {
            "fieldPath": "playlistId",
            "columnName": "playlistId",
            "affinity": "INTEGER",
            "notNull": true
          },
          {
            "fieldPath": "songId",
            "columnName": "songId",
            "affinity": "INTEGER",
            "notNull": true
          },
          {
            "fieldPath": "sortOrder",
            "columnName": "sortOrder",
            "affinity": "INTEGER",
            "notNull": true
          },
          {
            "fieldPath": "addedAt",
            "columnName": "addedAt",
            "affinity": "INTEGER",
            "notNull": true
          }
        ],
        "primaryKey": {
          "autoGenerate": false,
          "columnNames": [
            "playlistId",
            "songId"
          ]
        },
        "indices": [
          {
            "name": "index_playlist_songs_playlistId",
            "unique": false,
            "columnNames": [
              "playlistId"
            ],
            "orders": [],
            "createSql": "CREATE INDEX IF NOT EXISTS `index_playlist_songs_playlistId` ON `${TABLE_NAME}` (`playlistId`)"
          },
          {
            "name": "index_playlist_songs_songId",
            "unique": false,
            "columnNames": [
              "songId"
            ],
            "orders": [],
            "createSql": "CREATE INDEX IF NOT EXISTS `index_playlist_songs_songId` ON `${TABLE_NAME}` (`songId`)"
          }
        ],
        "foreignKeys": [
          {
            "table": "playlists",
            "onDelete": "CASCADE",
            "onUpdate": "NO ACTION",
            "columns": [
              "playlistId"
            ],
            "referencedColumns": [
              "id"
            ]
          }
        ]
      },
      {
        "tableName": "favorites",
        "createSql": "CREATE TABLE IF NOT EXISTS `${TABLE_NAME}` (`songId` INTEGER NOT NULL, `addedAt` INTEGER NOT NULL, PRIMARY KEY(`songId`))",
        "fields": [
          {
            "fieldPath": "songId",
            "columnName": "songId",
            "affinity": "INTEGER",
            "notNull": true
          },
          {
            "fieldPath": "addedAt",
            "columnName": "addedAt",
            "affinity": "INTEGER",
            "notNull": true
          }
        ],
        "primaryKey": {
          "autoGenerate": false,
          "columnNames": [
            "songId"
          ]
        }
      },
      {
        "tableName": "recents",
        "createSql": "CREATE TABLE IF NOT EXISTS `${TABLE_NAME}` (`songId` INTEGER NOT NULL, `playedAt` INTEGER NOT NULL, PRIMARY KEY(`songId`))",
        "fields": [
          {
            "fieldPath": "songId",
            "columnName": "songId",
            "affinity": "INTEGER",
            "notNull": true
          },
          {
            "fieldPath": "playedAt",
            "columnName": "playedAt",
            "affinity": "INTEGER",
            "notNull": true
          }
        ],
        "primaryKey": {
          "autoGenerate": false,
          "columnNames": [
            "songId"
          ]
        }
      },
      {
        "tableName": "play_counts",
        "createSql": "CREATE TABLE IF NOT EXISTS `${TABLE_NAME}` (`songId` INTEGER NOT NULL, `count` INTEGER NOT NULL, `lastPlayed` INTEGER NOT NULL, PRIMARY KEY(`songId`))",
        "fields": [
          {
            "fieldPath": "songId",
            "columnName": "songId",
            "affinity": "INTEGER",
            "notNull": true
          },
          {
            "fieldPath": "count",
            "columnName": "count",
            "affinity": "INTEGER",
            "notNull": true
          },
          {
            "fieldPath": "lastPlayed",
            "columnName": "lastPlayed",
            "affinity": "INTEGER",
            "notNull": true
          }
        ],
        "primaryKey": {
          "autoGenerate": false,
          "columnNames": [
            "songId"
          ]
        }
      }
    ],
    "setupQueries": [
      "CREATE TABLE IF NOT EXISTS room_master_table (id INTEGER PRIMARY KEY,identity_hash TEXT)",
      "INSERT OR REPLACE INTO room_master_table (id,identity_hash) VALUES(42, '3ef7bee3b1c15ce0649ace631416108c')"
    ]
  }
}